jaxpole/__init__.py
jaxpole/_modidx.py
jaxpole/filter.py
jaxpole/test_grad.py
jaxpole-0.0.3.dist-info/LICENSE
jaxpole-0.0.3.dist-info/METADATA
jaxpole-0.0.3.dist-info/WHEEL
jaxpole-0.0.3.dist-info/entry_points.txt
jaxpole-0.0.3.dist-info/top_level.txt
jaxpole-0.0.3.dist-info/RECORD
