Metadata-Version: 2.1
Name: jaxpole
Version: 0.0.3
Summary: A differentiable implementation of an all-pole filter in JAX
Home-page: https://github.com/rodrigodzf/jaxpole
Author: Rodrigo Diaz
Author-email: rodrigodzf@gmail.com
License: Apache Software License 2.0
Keywords: nbdev jupyter notebook python
Classifier: Development Status :: 4 - Beta
Classifier: Intended Audience :: Developers
Classifier: Natural Language :: English
Classifier: Programming Language :: Python :: 3.7
Classifier: Programming Language :: Python :: 3.8
Classifier: Programming Language :: Python :: 3.9
Classifier: Programming Language :: Python :: 3.10
Classifier: License :: OSI Approved :: Apache Software License
Requires-Python: >=3.7
License-File: LICENSE
Requires-Dist: jax[cpu]
Requires-Dist: numpy
Provides-Extra: dev
Requires-Dist: pytest ; extra == 'dev'
Requires-Dist: nbdev ; extra == 'dev'
